codexfix/__init__.py
codexfix/main.py
codexfix-0.3.3.dist-info/METADATA
codexfix-0.3.3.dist-info/WHEEL
codexfix-0.3.3.dist-info/entry_points.txt
codexfix-0.3.3.dist-info/licenses/LICENSE
codexfix-0.3.3.dist-info/RECORD
