Metadata-Version: 2.4
Name: codexfix
Version: 0.3.3
Summary: A powerful type-aware linter runner and Codex orchestrator that automatically fixes code issues using AI
Author-email: Ulrich Diedrichsen <uli@moinsen.dev>
License: MIT
License-File: LICENSE
Classifier: License :: OSI Approved :: MIT License
Classifier: Operating System :: OS Independent
Classifier: Programming Language :: Python :: 3
Classifier: Programming Language :: Python :: 3.13
Requires-Python: >=3.13
Requires-Dist: openai>=1.0.0
Requires-Dist: rich>=13.0.0
Provides-Extra: dev
Requires-Dist: black>=23.0.0; extra == 'dev'
Requires-Dist: mypy>=1.8.0; extra == 'dev'
Requires-Dist: pyright>=1.1.350; extra == 'dev'
